gym_open_poker/__init__.py
gym_open_poker/default/__init__.py
gym_open_poker/default/config.yaml
gym_open_poker/envs/__init__.py
gym_open_poker/envs/gym_open_poker.py
gym_open_poker/envs/img/C2.png
gym_open_poker/envs/img/C3.png
gym_open_poker/envs/img/C4.png
gym_open_poker/envs/img/C5.png
gym_open_poker/envs/img/C6.png
gym_open_poker/envs/img/C7.png
gym_open_poker/envs/img/C8.png
gym_open_poker/envs/img/C9.png
gym_open_poker/envs/img/CA.png
gym_open_poker/envs/img/CJ.png
gym_open_poker/envs/img/CK.png
gym_open_poker/envs/img/CQ.png
gym_open_poker/envs/img/CT.png
gym_open_poker/envs/img/Card.png
gym_open_poker/envs/img/D2.png
gym_open_poker/envs/img/D3.png
gym_open_poker/envs/img/D4.png
gym_open_poker/envs/img/D5.png
gym_open_poker/envs/img/D6.png
gym_open_poker/envs/img/D7.png
gym_open_poker/envs/img/D8.png
gym_open_poker/envs/img/D9.png
gym_open_poker/envs/img/DA.png
gym_open_poker/envs/img/DJ.png
gym_open_poker/envs/img/DK.png
gym_open_poker/envs/img/DQ.png
gym_open_poker/envs/img/DT.png
gym_open_poker/envs/img/H2.png
gym_open_poker/envs/img/H3.png
gym_open_poker/envs/img/H4.png
gym_open_poker/envs/img/H5.png
gym_open_poker/envs/img/H6.png
gym_open_poker/envs/img/H7.png
gym_open_poker/envs/img/H8.png
gym_open_poker/envs/img/H9.png
gym_open_poker/envs/img/HA.png
gym_open_poker/envs/img/HJ.png
gym_open_poker/envs/img/HK.png
gym_open_poker/envs/img/HQ.png
gym_open_poker/envs/img/HT.png
gym_open_poker/envs/img/S2.png
gym_open_poker/envs/img/S3.png
gym_open_poker/envs/img/S4.png
gym_open_poker/envs/img/S5.png
gym_open_poker/envs/img/S6.png
gym_open_poker/envs/img/S7.png
gym_open_poker/envs/img/S8.png
gym_open_poker/envs/img/S9.png
gym_open_poker/envs/img/SA.png
gym_open_poker/envs/img/SJ.png
gym_open_poker/envs/img/SK.png
gym_open_poker/envs/img/SQ.png
gym_open_poker/envs/img/ST.png
gym_open_poker/envs/img/__init__.py
gym_open_poker/envs/img/empty_card.png
gym_open_poker/envs/poker_util/__init__.py
gym_open_poker/envs/poker_util/action.py
gym_open_poker-0.0.48.dist-info/LICENSE
gym_open_poker-0.0.48.dist-info/METADATA
gym_open_poker-0.0.48.dist-info/WHEEL
gym_open_poker-0.0.48.dist-info/top_level.txt
gym_open_poker-0.0.48.dist-info/RECORD
